gps_helper/__init__.py
gps_helper/__version__.py
gps_helper/gps_helper.py
gps_helper/kalman.py
gps_helper/prn.py
gps_helper/prn_info.json
gps_helper/simulator.py
gps_helper/smoothing.py
gps_helper/tle_parsers.py
gps_helper-1.1.5.data/data/logo_hi.png
gps_helper-1.1.5.dist-info/LICENSE
gps_helper-1.1.5.dist-info/METADATA
gps_helper-1.1.5.dist-info/WHEEL
gps_helper-1.1.5.dist-info/top_level.txt
gps_helper-1.1.5.dist-info/RECORD
