Metadata-Version: 2.1
Name: gps_helper
Version: 1.1.5
Summary: GPS helper module
Home-page: https://github.com/gps-helper/gps-helper
Author: Chiranth Siddappa
Author-email: chiranthsiddappa@gmail.com
License: MIT
Requires-Python: >=3.5
License-File: LICENSE
Requires-Dist: numpy
Requires-Dist: sgp4
Provides-Extra: plotting
Requires-Dist: matplotlib ; extra == 'plotting'
Requires-Dist: mayavi ; extra == 'plotting'
